{
  "noticias": [
    {
      "titulo": "Anac alerta para riscos de trotes com óleo após morte de aluno de aviação",
      "imagem": null
    },
    {
      "titulo": "No RS, ventos causam estragos em 18 cidades, com danos em telhados e quedas de árvores",
      "imagem": null
    },
    {
      "titulo": "Inglaterra bate França por 6 a 4 e conquista 3º lugar inédito na Copa do Mundo",
      "imagem": null
    },
    {
      "titulo": "Beatriz Almeida vence o Musclecontest Brazil 2026 na Figure",
      "imagem": null
    },
    {
      "titulo": "Estilista gaúcha cria vestido de noiva com quase 3 mil papéis descartados de figurinhas da Copa",
      "imagem": null
    },
    {
      "titulo": "Duelo de dez gols entre Inglaterra e França estabelece recorde na disputa do terceiro lugar",
      "imagem": null
    },
    {
      "titulo": "Em jogo com 10 gols, Inglaterra confirma 3º lugar na Copa sobre a França",
      "imagem": null
    },
    {
      "titulo": "Inglaterra vence França (6-4) e termina em 3º lugar na Copa de 2026",
      "imagem": null
    },
    {
      "titulo": "Mbappé faz dois gols contra a Inglaterra e ultrapassa Messi na artilharia da Copa",
      "imagem": null
    },
    {
      "titulo": "Ao menos 470 pessoas morreram sob custódia em regime de exceção de El Salvador, diz ONG",
      "imagem": null
    },
    {
      "titulo": "Livinho se torna bicampeão do Musclecontest Brazil",
      "imagem": null
    },
    {
      "titulo": "Torcedores argentinos transformam Times Square em arquibancada na véspera da final da Copa",
      "imagem": null
    },
    {
      "titulo": "EUA lança novos ataques aéreos contra Irã",
      "imagem": null
    },
    {
      "titulo": "Mostra de teatro lambe-lambe apresenta cenas em miniatura em Rio Preto",
      "imagem": null
    },
    {
      "titulo": "Várias explosões são ouvidas na capital da Ucrânia",
      "imagem": null
    }
  ],
  "atualizadoEm": "2026-07-18T23:36:33.650Z"
}